astroML/__init__.py
astroML/conftest.py
astroML/correlation.py
astroML/cosmology.py
astroML/crossmatch.py
astroML/decorators.py
astroML/filters.py
astroML/fourier.py
astroML/lumfunc.py
astroML/resample.py
astroML/sum_of_norms.py
astroML/classification/__init__.py
astroML/classification/gmm_bayes.py
astroML/classification/tests/__init__.py
astroML/classification/tests/test_gmm_bayes.py
astroML/clustering/__init__.py
astroML/clustering/mst_clustering.py
astroML/clustering/tests/__init__.py
astroML/clustering/tests/test_MST_clustering.py
astroML/datasets/LIGO_bigdog.py
astroML/datasets/LINEAR_sample.py
astroML/datasets/__init__.py
astroML/datasets/dr7_quasar.py
astroML/datasets/generated.py
astroML/datasets/hogg2010test.py
astroML/datasets/imaging_sample.py
astroML/datasets/kelly2007test.py
astroML/datasets/moving_objects.py
astroML/datasets/nasa_atlas.py
astroML/datasets/rrlyrae_mags.py
astroML/datasets/rrlyrae_templates.py
astroML/datasets/sdss_S82standards.py
astroML/datasets/sdss_corrected_spectra.py
astroML/datasets/sdss_filters.py
astroML/datasets/sdss_galaxy_colors.py
astroML/datasets/sdss_galaxy_images.py
astroML/datasets/sdss_specgals.py
astroML/datasets/sdss_spectrum.py
astroML/datasets/sdss_sspp.py
astroML/datasets/wmap_temperatures.py
astroML/datasets/tests/__init__.py
astroML/datasets/tests/test_datasets.py
astroML/datasets/tools/__init__.py
astroML/datasets/tools/cas_query.py
astroML/datasets/tools/download.py
astroML/datasets/tools/sdss_fits.py
astroML/datasets/tools/sql_query.py
astroML/density_estimation/__init__.py
astroML/density_estimation/bayesian_blocks.py
astroML/density_estimation/density_estimation.py
astroML/density_estimation/empirical.py
astroML/density_estimation/gauss_mixture.py
astroML/density_estimation/histtools.py
astroML/density_estimation/xdeconv.py
astroML/density_estimation/tests/__init__.py
astroML/density_estimation/tests/test_bayesian_blocks.py
astroML/density_estimation/tests/test_density.py
astroML-1.0.2.post1.dist-info/LICENSE.rst
astroML-1.0.2.post1.dist-info/METADATA
astroML-1.0.2.post1.dist-info/WHEEL
astroML-1.0.2.post1.dist-info/top_level.txt
astroML-1.0.2.post1.dist-info/RECORD
