Metadata-Version: 2.1
Name: astroML
Version: 1.0.2.post1
Summary: Tools for machine learning and data mining in Astronomy
Home-page: http://astroML.github.com
Author: Jake VanderPlas
Author-email: vanderplas@astro.washington.edu
Maintainer: Brigitta Sipocz
Maintainer-email: bsipocz@gmail.com
License: BSD 3-Clause License
Keywords: astronomy,astrophysics,cosmology,space,science,modeling,models,fitting,machine-learning
Platform: UNKNOWN
Classifier: Development Status :: 4 - Beta
Classifier: Environment :: Console
Classifier: Intended Audience :: Science/Research
Classifier: License :: OSI Approved :: BSD License
Classifier: Natural Language :: English
Classifier: Programming Language :: Python :: 3
Classifier: Programming Language :: Python :: 3.5
Classifier: Programming Language :: Python :: 3.6
Classifier: Programming Language :: Python :: 3.7
Classifier: Programming Language :: Python :: 3.8
Classifier: Programming Language :: Python :: 3 :: Only
Classifier: Topic :: Scientific/Engineering :: Astronomy
Provides-Extra: test
Provides-Extra: all
Provides-Extra: codestyle
Provides-Extra: docs
